LICENSE
README.md
setup.cfg
setup.py
isa/RtcsharePlugin.py
isa/__init__.py
isa/_find_singular_file_in_dir.py
isa/_project_config.py
isa/add.py
isa/auto_detect_vocalizations.py
isa/cli.py
isa/create_spectrograms.py
isa/init.py
isa/update.py
isa/version.py
isa_ssl.egg-info/PKG-INFO
isa_ssl.egg-info/SOURCES.txt
isa_ssl.egg-info/dependency_links.txt
isa_ssl.egg-info/entry_points.txt
isa_ssl.egg-info/requires.txt
isa_ssl.egg-info/top_level.txt