Metadata-Version: 2.1
Name: isa-ssl
Version: 0.2.1
Summary: Isa (Ee-suh) is a visualization and annotation tool for sound source location.
Home-page: https://github.com/scratchrealm/isa
Author: Jeremy Magland and Ralph Peterson
Author-email: jmagland@flatironinstitute.org
Project-URL: Bug Tracker, https://github.com/scratchrealm/isa/issues
Classifier: Programming Language :: Python :: 3
Classifier: License :: OSI Approved :: Apache Software License
Classifier: Operating System :: OS Independent
License-File: LICENSE
